{"id":"a7f419e6-0d9e-4ebf-ac92-521d7cb1d085","name":"READY-MIX CONCRETE produced by NUOVA DEMI and CAVA SURIANA: RCK 25 Brembate","declared_unit":"M3","version":"1.1","published_date":1640995200,"valid_until":1798761600,"format_version":"1.1.5","source":null,"reference_service_life":null,"standard":"EN15804A2","comment":null,"location":"IT","subtype":"Specific","conversions":[],"gwp":{"a1a3":null,"a4":null,"a5":null,"b1":null,"b2":null,"b3":null,"b4":null,"b5":null,"b6":null,"b7":null,"c1":0.69,"c2":0.0105,"c3":1.82,"c4":0.573,"d":0.0},"odp":{"a1a3":null,"a4":null,"a5":null,"b1":null,"b2":null,"b3":null,"b4":null,"b5":null,"b6":null,"b7":null,"c1":1.47e-7,"c2":2.37e-9,"c3":3.88e-7,"c4":1.73e-7,"d":0.0},"ap":{"a1a3":null,"a4":null,"a5":null,"b1":null,"b2":null,"b3":null,"b4":null,"b5":null,"b6":null,"b7":null,"c1":0.00717,"c2":0.0000509,"c3":0.0188,"c4":0.0048,"d":0.0},"ep":null,"pocp":{"a1a3":null,"a4":null,"a5":null,"b1":null,"b2":null,"b3":null,"b4":null,"b5":null,"b6":null,"b7":null,"c1":0.00957,"c2":0.0000531,"c3":0.0251,"c4":0.00521,"d":0.0},"adpe":{"a1a3":null,"a4":null,"a5":null,"b1":null,"b2":null,"b3":null,"b4":null,"b5":null,"b6":null,"b7":null,"c1":3.55e-7,"c2":4.79e-8,"c3":9.61e-7,"c4":1.86e-6,"d":0.0},"adpf":{"a1a3":null,"a4":null,"a5":null,"b1":null,"b2":null,"b3":null,"b4":null,"b5":null,"b6":null,"b7":null,"c1":9.47,"c2":0.157,"c3":24.9,"c4":13.4,"d":0.0},"penre":{"a1a3":null,"a4":null,"a5":null,"b1":null,"b2":null,"b3":null,"b4":null,"b5":null,"b6":null,"b7":null,"c1":10.0,"c2":0.164,"c3":26.3,"c4":14.0,"d":0.0},"pere":{"a1a3":null,"a4":null,"a5":null,"b1":null,"b2":null,"b3":null,"b4":null,"b5":null,"b6":null,"b7":null,"c1":0.0532,"c2":0.00265,"c3":0.141,"c4":0.228,"d":0.0},"perm":{"a1a3":null,"a4":null,"a5":null,"b1":null,"b2":null,"b3":null,"b4":null,"b5":null,"b6":null,"b7":null,"c1":0.0,"c2":0.0,"c3":0.0,"c4":0.0,"d":0.0},"pert":null,"penrt":{"a1a3":null,"a4":null,"a5":null,"b1":null,"b2":null,"b3":null,"b4":null,"b5":null,"b6":null,"b7":null,"c1":10.1,"c2":0.167,"c3":26.5,"c4":14.2,"d":0.0},"penrm":{"a1a3":null,"a4":null,"a5":null,"b1":null,"b2":null,"b3":null,"b4":null,"b5":null,"b6":null,"b7":null,"c1":0.0,"c2":0.0,"c3":0.0,"c4":0.0,"d":0.0},"sm":{"a1a3":null,"a4":null,"a5":null,"b1":null,"b2":null,"b3":null,"b4":null,"b5":null,"b6":null,"b7":null,"c1":0.0,"c2":0.0,"c3":0.0,"c4":0.0,"d":0.0},"rsf":{"a1a3":null,"a4":null,"a5":null,"b1":null,"b2":null,"b3":null,"b4":null,"b5":null,"b6":null,"b7":null,"c1":0.0,"c2":0.0,"c3":0.0,"c4":0.0,"d":0.0},"nrsf":{"a1a3":null,"a4":null,"a5":null,"b1":null,"b2":null,"b3":null,"b4":null,"b5":null,"b6":null,"b7":null,"c1":0.0,"c2":0.0,"c3":0.0,"c4":0.0,"d":0.0},"fw":{"a1a3":null,"a4":null,"a5":null,"b1":null,"b2":null,"b3":null,"b4":null,"b5":null,"b6":null,"b7":null,"c1":0.00054,"c2":0.0000199,"c3":0.00143,"c4":0.0141,"d":0.0},"hwd":{"a1a3":null,"a4":null,"a5":null,"b1":null,"b2":null,"b3":null,"b4":null,"b5":null,"b6":null,"b7":null,"c1":0.0000259,"c2":4.21e-7,"c3":0.0000682,"c4":0.0000207,"d":0.0},"nhwd":{"a1a3":null,"a4":null,"a5":null,"b1":null,"b2":null,"b3":null,"b4":null,"b5":null,"b6":null,"b7":null,"c1":0.0126,"c2":0.00666,"c3":0.0373,"c4":54.1,"d":0.0},"rwd":{"a1a3":null,"a4":null,"a5":null,"b1":null,"b2":null,"b3":null,"b4":null,"b5":null,"b6":null,"b7":null,"c1":0.0000654,"c2":1.05e-6,"c3":0.000172,"c4":0.0000798,"d":0.0},"cru":{"a1a3":null,"a4":null,"a5":null,"b1":null,"b2":null,"b3":null,"b4":null,"b5":null,"b6":null,"b7":null,"c1":0.0,"c2":0.0,"c3":0.0,"c4":0.0,"d":0.0},"mfr":{"a1a3":null,"a4":null,"a5":null,"b1":null,"b2":null,"b3":null,"b4":null,"b5":null,"b6":null,"b7":null,"c1":0.0,"c2":0.0,"c3":2.45,"c4":0.0,"d":0.0},"mer":{"a1a3":null,"a4":null,"a5":null,"b1":null,"b2":null,"b3":null,"b4":null,"b5":null,"b6":null,"b7":null,"c1":0.0,"c2":0.0,"c3":0.0,"c4":0.0,"d":0.0},"eee":{"a1a3":null,"a4":null,"a5":null,"b1":null,"b2":null,"b3":null,"b4":null,"b5":null,"b6":null,"b7":null,"c1":0.0,"c2":0.0,"c3":0.0,"c4":0.0,"d":0.0},"eet":{"a1a3":null,"a4":null,"a5":null,"b1":null,"b2":null,"b3":null,"b4":null,"b5":null,"b6":null,"b7":null,"c1":0.0,"c2":0.0,"c3":0.0,"c4":0.0,"d":0.0},"meta_data":null}