{"id":"c7520a8b-97de-4d43-9413-9bbb0bf1c6a9","name":"Aluminium profiles for doors and windows – series: CX700HP  CX70.415","declared_unit":"KG","version":"1.1","published_date":1609459200,"valid_until":1767225600,"format_version":"1.1.5","source":null,"reference_service_life":null,"standard":"EN15804A2","comment":null,"location":"IT","subtype":"Specific","conversions":[],"gwp":{"a1a3":6.7612,"a4":null,"a5":null,"b1":null,"b2":null,"b3":null,"b4":null,"b5":null,"b6":null,"b7":null,"c1":0.0,"c2":0.0256,"c3":0.0,"c4":0.0,"d":-3.9708},"odp":{"a1a3":0.0,"a4":null,"a5":null,"b1":null,"b2":null,"b3":null,"b4":null,"b5":null,"b6":null,"b7":null,"c1":0.0,"c2":0.0,"c3":0.0,"c4":0.0,"d":0.0},"ap":{"a1a3":0.0177,"a4":null,"a5":null,"b1":null,"b2":null,"b3":null,"b4":null,"b5":null,"b6":null,"b7":null,"c1":0.0,"c2":0.0001,"c3":0.0,"c4":0.0,"d":-0.0033},"ep":null,"pocp":{"a1a3":0.0112,"a4":null,"a5":null,"b1":null,"b2":null,"b3":null,"b4":null,"b5":null,"b6":null,"b7":null,"c1":0.0,"c2":0.0001,"c3":0.0,"c4":0.0,"d":-0.001},"adpe":{"a1a3":0.0005,"a4":null,"a5":null,"b1":null,"b2":null,"b3":null,"b4":null,"b5":null,"b6":null,"b7":null,"c1":0.0,"c2":0.0,"c3":0.0,"c4":0.0,"d":-0.0003},"adpf":{"a1a3":113.33,"a4":null,"a5":null,"b1":null,"b2":null,"b3":null,"b4":null,"b5":null,"b6":null,"b7":null,"c1":0.0,"c2":0.378,"c3":0.0,"c4":0.0,"d":-79.9875},"penre":{"a1a3":118.5256,"a4":null,"a5":null,"b1":null,"b2":null,"b3":null,"b4":null,"b5":null,"b6":null,"b7":null,"c1":0.0,"c2":0.3781,"c3":0.0,"c4":0.0,"d":0.0},"pere":{"a1a3":5.0547,"a4":null,"a5":null,"b1":null,"b2":null,"b3":null,"b4":null,"b5":null,"b6":null,"b7":null,"c1":0.0,"c2":0.0024,"c3":0.0,"c4":0.0,"d":0.0},"perm":{"a1a3":0.01,"a4":null,"a5":null,"b1":null,"b2":null,"b3":null,"b4":null,"b5":null,"b6":null,"b7":null,"c1":0.0,"c2":0.0,"c3":0.0,"c4":0.0,"d":0.0},"pert":null,"penrt":{"a1a3":118.5336,"a4":null,"a5":null,"b1":null,"b2":null,"b3":null,"b4":null,"b5":null,"b6":null,"b7":null,"c1":0.0,"c2":0.3781,"c3":0.0,"c4":0.0,"d":-12.4332},"penrm":{"a1a3":0.0081,"a4":null,"a5":null,"b1":null,"b2":null,"b3":null,"b4":null,"b5":null,"b6":null,"b7":null,"c1":0.0,"c2":0.0,"c3":0.0,"c4":0.0,"d":0.0},"sm":{"a1a3":0.0,"a4":null,"a5":null,"b1":null,"b2":null,"b3":null,"b4":null,"b5":null,"b6":null,"b7":null,"c1":0.0,"c2":0.0,"c3":0.0,"c4":0.0,"d":0.0},"rsf":{"a1a3":1.5173,"a4":null,"a5":null,"b1":null,"b2":null,"b3":null,"b4":null,"b5":null,"b6":null,"b7":null,"c1":0.0,"c2":0.0018,"c3":0.0,"c4":0.0,"d":0.0},"nrsf":{"a1a3":0.001,"a4":null,"a5":null,"b1":null,"b2":null,"b3":null,"b4":null,"b5":null,"b6":null,"b7":null,"c1":0.0,"c2":0.0,"c3":0.0,"c4":0.0,"d":-60.0003},"fw":{"a1a3":1.8375,"a4":null,"a5":null,"b1":null,"b2":null,"b3":null,"b4":null,"b5":null,"b6":null,"b7":null,"c1":0.0,"c2":0.0027,"c3":0.0,"c4":0.0,"d":0.0},"hwd":{"a1a3":0.0121,"a4":null,"a5":null,"b1":null,"b2":null,"b3":null,"b4":null,"b5":null,"b6":null,"b7":null,"c1":0.0,"c2":0.0,"c3":0.0,"c4":0.0,"d":0.0},"nhwd":{"a1a3":3.2938,"a4":null,"a5":null,"b1":null,"b2":null,"b3":null,"b4":null,"b5":null,"b6":null,"b7":null,"c1":0.0,"c2":0.0114,"c3":0.0,"c4":0.0,"d":0.0},"rwd":{"a1a3":0.0003,"a4":null,"a5":null,"b1":null,"b2":null,"b3":null,"b4":null,"b5":null,"b6":null,"b7":null,"c1":0.0,"c2":0.0,"c3":0.0,"c4":0.0,"d":0.0},"cru":{"a1a3":0.0,"a4":null,"a5":null,"b1":null,"b2":null,"b3":null,"b4":null,"b5":null,"b6":null,"b7":null,"c1":0.0,"c2":0.0,"c3":0.0,"c4":0.0,"d":0.0},"mfr":{"a1a3":0.0,"a4":null,"a5":null,"b1":null,"b2":null,"b3":null,"b4":null,"b5":null,"b6":null,"b7":null,"c1":0.0,"c2":0.0,"c3":0.0,"c4":0.0,"d":-0.6373},"mer":{"a1a3":0.0,"a4":null,"a5":null,"b1":null,"b2":null,"b3":null,"b4":null,"b5":null,"b6":null,"b7":null,"c1":0.0,"c2":0.0,"c3":0.0,"c4":0.0,"d":0.0455},"eee":{"a1a3":0.0,"a4":null,"a5":null,"b1":null,"b2":null,"b3":null,"b4":null,"b5":null,"b6":null,"b7":null,"c1":0.0,"c2":0.0,"c3":0.0,"c4":0.0,"d":0.0},"eet":{"a1a3":0.0,"a4":null,"a5":null,"b1":null,"b2":null,"b3":null,"b4":null,"b5":null,"b6":null,"b7":null,"c1":0.0,"c2":0.0,"c3":0.0,"c4":0.0,"d":0.0},"meta_data":null}