{"id":"ecf3a5e3-63f4-4cca-9b4d-d05c707a3263","name":"Pavimenti in legno Collezione Garbelotto SP09","declared_unit":"M2","version":"1.1","published_date":1546300800,"valid_until":1767225600,"format_version":"1.1.5","source":null,"reference_service_life":null,"standard":"EN15804A1","comment":null,"location":"GLO","subtype":"Specific","conversions":[],"gwp":{"a1a3":null,"a4":null,"a5":4.78,"b1":null,"b2":null,"b3":null,"b4":null,"b5":null,"b6":null,"b7":null,"c1":null,"c2":null,"c3":null,"c4":null,"d":null},"odp":{"a1a3":null,"a4":null,"a5":5.49e-7,"b1":null,"b2":null,"b3":null,"b4":null,"b5":null,"b6":null,"b7":null,"c1":null,"c2":null,"c3":null,"c4":null,"d":null},"ap":{"a1a3":null,"a4":null,"a5":0.0176,"b1":null,"b2":null,"b3":null,"b4":null,"b5":null,"b6":null,"b7":null,"c1":null,"c2":null,"c3":null,"c4":null,"d":null},"ep":{"a1a3":null,"a4":null,"a5":0.00859,"b1":null,"b2":null,"b3":null,"b4":null,"b5":null,"b6":null,"b7":null,"c1":null,"c2":null,"c3":null,"c4":null,"d":null},"pocp":{"a1a3":null,"a4":null,"a5":0.00256,"b1":null,"b2":null,"b3":null,"b4":null,"b5":null,"b6":null,"b7":null,"c1":null,"c2":null,"c3":null,"c4":null,"d":null},"adpe":{"a1a3":null,"a4":null,"a5":0.0000196,"b1":null,"b2":null,"b3":null,"b4":null,"b5":null,"b6":null,"b7":null,"c1":null,"c2":null,"c3":null,"c4":null,"d":null},"adpf":{"a1a3":null,"a4":null,"a5":85.68,"b1":null,"b2":null,"b3":null,"b4":null,"b5":null,"b6":null,"b7":null,"c1":null,"c2":null,"c3":null,"c4":null,"d":null},"penre":{"a1a3":null,"a4":null,"a5":62.74,"b1":null,"b2":null,"b3":null,"b4":null,"b5":null,"b6":null,"b7":null,"c1":null,"c2":null,"c3":null,"c4":null,"d":null},"pere":{"a1a3":null,"a4":null,"a5":3.6,"b1":null,"b2":null,"b3":null,"b4":null,"b5":null,"b6":null,"b7":null,"c1":null,"c2":null,"c3":null,"c4":null,"d":null},"perm":{"a1a3":null,"a4":null,"a5":0.0,"b1":null,"b2":null,"b3":null,"b4":null,"b5":null,"b6":null,"b7":null,"c1":null,"c2":null,"c3":null,"c4":null,"d":null},"pert":{"a1a3":null,"a4":null,"a5":3.6,"b1":null,"b2":null,"b3":null,"b4":null,"b5":null,"b6":null,"b7":null,"c1":null,"c2":null,"c3":null,"c4":null,"d":null},"penrt":{"a1a3":null,"a4":null,"a5":99.94,"b1":null,"b2":null,"b3":null,"b4":null,"b5":null,"b6":null,"b7":null,"c1":null,"c2":null,"c3":null,"c4":null,"d":null},"penrm":{"a1a3":null,"a4":null,"a5":37.2,"b1":null,"b2":null,"b3":null,"b4":null,"b5":null,"b6":null,"b7":null,"c1":null,"c2":null,"c3":null,"c4":null,"d":null},"sm":{"a1a3":null,"a4":null,"a5":0.0,"b1":null,"b2":null,"b3":null,"b4":null,"b5":null,"b6":null,"b7":null,"c1":null,"c2":null,"c3":null,"c4":null,"d":null},"rsf":{"a1a3":null,"a4":null,"a5":0.0,"b1":null,"b2":null,"b3":null,"b4":null,"b5":null,"b6":null,"b7":null,"c1":null,"c2":null,"c3":null,"c4":null,"d":null},"nrsf":{"a1a3":null,"a4":null,"a5":0.0,"b1":null,"b2":null,"b3":null,"b4":null,"b5":null,"b6":null,"b7":null,"c1":null,"c2":null,"c3":null,"c4":null,"d":null},"fw":{"a1a3":null,"a4":null,"a5":0.000599,"b1":null,"b2":null,"b3":null,"b4":null,"b5":null,"b6":null,"b7":null,"c1":null,"c2":null,"c3":null,"c4":null,"d":null},"hwd":{"a1a3":null,"a4":null,"a5":0.0000597,"b1":null,"b2":null,"b3":null,"b4":null,"b5":null,"b6":null,"b7":null,"c1":null,"c2":null,"c3":null,"c4":null,"d":null},"nhwd":{"a1a3":null,"a4":null,"a5":0.644,"b1":null,"b2":null,"b3":null,"b4":null,"b5":null,"b6":null,"b7":null,"c1":null,"c2":null,"c3":null,"c4":null,"d":null},"rwd":{"a1a3":null,"a4":null,"a5":0.000135,"b1":null,"b2":null,"b3":null,"b4":null,"b5":null,"b6":null,"b7":null,"c1":null,"c2":null,"c3":null,"c4":null,"d":null},"cru":{"a1a3":null,"a4":null,"a5":0.0,"b1":null,"b2":null,"b3":null,"b4":null,"b5":null,"b6":null,"b7":null,"c1":null,"c2":null,"c3":null,"c4":null,"d":null},"mfr":{"a1a3":null,"a4":null,"a5":0.5,"b1":null,"b2":null,"b3":null,"b4":null,"b5":null,"b6":null,"b7":null,"c1":null,"c2":null,"c3":null,"c4":null,"d":null},"mer":{"a1a3":null,"a4":null,"a5":0.0,"b1":null,"b2":null,"b3":null,"b4":null,"b5":null,"b6":null,"b7":null,"c1":null,"c2":null,"c3":null,"c4":null,"d":null},"eee":{"a1a3":null,"a4":null,"a5":0.0,"b1":null,"b2":null,"b3":null,"b4":null,"b5":null,"b6":null,"b7":null,"c1":null,"c2":null,"c3":null,"c4":null,"d":null},"eet":{"a1a3":null,"a4":null,"a5":0.0,"b1":null,"b2":null,"b3":null,"b4":null,"b5":null,"b6":null,"b7":null,"c1":null,"c2":null,"c3":null,"c4":null,"d":null},"meta_data":null}